{
  "recommended": "9c2ad9a",
  "latest": "9c2ad9a",
  "blobs": [
    {
      "build": "9c2ad9a",
      "build_date": "20230922",
      "status": "Stable",
      "changelog": "- State class warnings in HA fixed.<br/>- Align sensor names to latest Home Assistant release rules.<br/>- Current gauges cards in web UI.<br/>- AWS IoT Core/MQTT TLS support.<br/>- Optional JSON payload for sensor states. <b>NOTE! Do not enable json payload if you already have statistics in Home Assistant. It will be removed and the power meters import energy (kWh) will be sampled as todays consumtion from day 0.</b>",
      "blob": "blobs/9c2ad9a.bin"
    },
    {
      "build": "a5566e0",
      "build_date": "20240211",
      "status": "Development",
      "changelog": "- Fix issue when AP SSID is hidden.<br/>- Increase mqtt password length.<br/>- Add ethernet support (P1IB-eth).<br/>- improve STAR-meters corrupt data compensation.<br/>- Improve wifi connection/reconnect behavior<br/>- HA auto discovery UI switch.<br/>- JSON payload improvements.<br/>",
      "blob": "blobs/a5566e0.bin"
    }
  ]
}
